{
  "system": "Reality Reset OS",
  "status": "active",
    "updated_utc": "",
  "last_run_minutes_ago": null,

  "system_health": {
    "ok": true,
    "notes": "initial live state"
  },

  "signals": {
    "market_os": {
      "enabled": true,
      "state": "idle"
    },
    "medical_os": {
      "enabled": true,
      "state": "idle"
    },
    "pressure_index": {
      "enabled": true,
      "state": "calibrating"
    }
  },

  "metrics": {
    "confidence_level": null,
    "translation_lag": null
  },

  "alerts": [],

  "notes": "Live bridge established. Awaiting updater."
}